{
    "Level": 1,
    "Experience": 0,
    "Name": "Grinning Goblins #1158",
    "Description": "Common Goblin Warrior",
    "Rank": "Warrior",
    "Faction": "Lords Alliance",
    "Body": "Skinny",
    "Last Trained": 0,
    "Base Stats": {
        "Strength": 3,
        "Dexterity": 13,
        "Constitution": 5,
        "Wisdom": 5,
        "Luck": 6
    },
    "Battle Stats": {
        "Attack Damage": 9.3,
        "Attack Speed": 26.6,
        "Accuracy": 24,
        "Evasion": 24,
        "Defence": 0,
        "Health": 50
    }
}