{
    "Level": 1,
    "Experience": 0,
    "Name": "Grinning Goblins #1421",
    "Description": "Uncommon Goblin Warrior",
    "Rank": "Warrior",
    "Faction": "Old King",
    "Body": "Average",
    "Last Trained": 0,
    "Base Stats": {
        "Strength": 5,
        "Dexterity": 7,
        "Constitution": 5,
        "Wisdom": 5,
        "Luck": 7
    },
    "Battle Stats": {
        "Attack Damage": 10.4,
        "Attack Speed": 20.55,
        "Accuracy": 19,
        "Evasion": 14.05,
        "Defence": 2.75,
        "Health": 50
    }
}